neural_chemistry/__init__.py
neural_chemistry/emulator.py
neural_chemistry/encoding.py
neural_chemistry/mlp.py
neural_chemistry/normalization.py
neural_chemistry/weights/weights.pth
neural_chemistry-1.0.0.dist-info/METADATA
neural_chemistry-1.0.0.dist-info/WHEEL
neural_chemistry-1.0.0.dist-info/RECORD
