Metadata-Version: 2.3
Name: neural-chemistry
Version: 1.0.0
Summary: Add your description here
Author-email: Andres Asensio Ramos <aasensio@iac.es>
Requires-Python: >=3.10
Requires-Dist: numpy
Requires-Dist: scipy
Requires-Dist: tqdm
